keyring_configparser/__init__.py
keyring_configparser/keyring_configpaser.py
keyring_configparser/keyring_interpolation.py
keyring_configparser-1.0.0.dist-info/METADATA
keyring_configparser-1.0.0.dist-info/WHEEL
keyring_configparser-1.0.0.dist-info/licenses/LICENSE
keyring_configparser-1.0.0.dist-info/RECORD
