Metadata-Version: 2.1
Name: keyring_configparser
Version: 1.0.0
Summary: A ConfigParser subclass that can read values stored with the keyring pypi package.
Project-URL: Homepage, https://github.com/LiamMahoney/keyring_configparser/
Project-URL: Bug Tracker, https://github.com/LiamMahoney/keyring_configparser/issues/
Author-email: Liam Mahoney <liammahoney96@gmail.com>
License-File: LICENSE
Classifier: License :: OSI Approved :: MIT License
Classifier: Operating System :: OS Independent
Classifier: Programming Language :: Python :: 3
Requires-Python: >=3.7
Requires-Dist: keyring>=23.13.1
